nastranio/.coverage
nastranio/__init__.py
nastranio/cards/__init__.py
nastranio/cards/axis.py
nastranio/cards/elements.py
nastranio/cards/loading.py
nastranio/cards/materials.py
nastranio/cards/properties.py
nastranio/cards/types.py
nastranio/cardslib.py
nastranio/cli.py
nastranio/clib.c
nastranio/clib.cpython-38-x86_64-linux-gnu.so
nastranio/clib.cpython-39-x86_64-linux-gnu.so
nastranio/constants.py
nastranio/decorators.py
nastranio/fields_writer.py
nastranio/htmlcov/.gitignore
nastranio/htmlcov/__init___py.html
nastranio/htmlcov/cardslib_py.html
nastranio/htmlcov/class_index.html
nastranio/htmlcov/cli_py.html
nastranio/htmlcov/constants_py.html
nastranio/htmlcov/coverage_html_cb_6fb7b396.js
nastranio/htmlcov/decorators_py.html
nastranio/htmlcov/favicon_32_cb_58284776.png
nastranio/htmlcov/fields_writer_py.html
nastranio/htmlcov/function_index.html
nastranio/htmlcov/index.html
nastranio/htmlcov/keybd_closed_cb_ce680311.png
nastranio/htmlcov/pylib_py.html
nastranio/htmlcov/registry_py.html
nastranio/htmlcov/serializer_py.html
nastranio/htmlcov/status.json
nastranio/htmlcov/style_cb_8e611ae1.css
nastranio/htmlcov/types_py.html
nastranio/htmlcov/utils_py.html
nastranio/htmlcov/z_3759a37abe5f3700___init___py.html
nastranio/htmlcov/z_4fc25cff4091330d___init___py.html
nastranio/htmlcov/z_4fc25cff4091330d_user_input_v1_py.html
nastranio/htmlcov/z_4fc25cff4091330d_user_input_v2_py.html
nastranio/htmlcov/z_68030a1d559e6ebd___init___py.html
nastranio/htmlcov/z_68030a1d559e6ebd_bulk_py.html
nastranio/htmlcov/z_68030a1d559e6ebd_op2_py.html
nastranio/htmlcov/z_c40a35bfe1af215b___init___py.html
nastranio/htmlcov/z_c40a35bfe1af215b_femap_neutral_py.html
nastranio/htmlcov/z_dbe80666834a98a3___init___py.html
nastranio/htmlcov/z_dbe80666834a98a3_gmsh_py.html
nastranio/htmlcov/z_dbe80666834a98a3_mixins_py.html
nastranio/htmlcov/z_dbe80666834a98a3_study_py.html
nastranio/htmlcov/z_dbe80666834a98a3_user_input_py.html
nastranio/htmlcov/z_e2fe60ed9e48474f___init___py.html
nastranio-0.21.4.dist-info/AUTHORS.rst
nastranio-0.21.4.dist-info/LICENSE
nastranio-0.21.4.dist-info/METADATA
nastranio-0.21.4.dist-info/WHEEL
nastranio-0.21.4.dist-info/entry_points.txt
nastranio-0.21.4.dist-info/RECORD
