Metadata-Version: 2.1
Name: nastranio
Version: 0.21.4
Summary: 
Author: Nicolas Cordier
Author-email: nicolas.cordier@numeric-gmbh.ch
Requires-Python: >=3.11,<3.12
Classifier: Programming Language :: Python :: 3
Classifier: Programming Language :: Python :: 3.11
Requires-Dist: Click
Requires-Dist: colorama
Requires-Dist: cpylog
Requires-Dist: deepdiff (>=5.8.1,<6.0.0)
Requires-Dist: gridsource
Requires-Dist: jinja2 (>=3.1,<4.0)
Requires-Dist: msgpack
Requires-Dist: msgpack-numpy
Requires-Dist: networkx
Requires-Dist: numtools
Requires-Dist: pandas
Requires-Dist: pyNastran (>=1.3,<2.0)
Requires-Dist: pyvista (>=0.43,<0.44)
Requires-Dist: pyyaml
Requires-Dist: rtree (>=1.1,<2.0)
Requires-Dist: tqdm
Requires-Dist: vg
Requires-Dist: vtk (==9.3.1)
